addroni/__init__.py
addroni-0.0.1.dist-info/LICENSE.txt
addroni-0.0.1.dist-info/METADATA
addroni-0.0.1.dist-info/WHEEL
addroni-0.0.1.dist-info/top_level.txt
addroni-0.0.1.dist-info/RECORD
